basemath_analysis/__init__.py
basemath_analysis/basemath.py
basemath_analysis-0.1.1.dist-info/LICENSE
basemath_analysis-0.1.1.dist-info/METADATA
basemath_analysis-0.1.1.dist-info/WHEEL
basemath_analysis-0.1.1.dist-info/RECORD
