Metadata-Version: 2.1
Name: basemath-analysis
Version: 0.1.1
Summary: A library for BaseMath's test, a novel Group Sequential Testing approach that enables the user to stop early.
Home-page: https://github.com/getyourguide/basemath
License: Apache-2.0
Author: Data Products GYG
Author-email: engineering.data-products@getyourguide.com
Requires-Python: >=3.8,<4.0
Classifier: License :: OSI Approved :: Apache Software License
Classifier: Programming Language :: Python :: 3
Classifier: Programming Language :: Python :: 3.8
Classifier: Programming Language :: Python :: 3.9
Classifier: Programming Language :: Python :: 3.10
Classifier: Programming Language :: Python :: 3.11
Classifier: Programming Language :: Python :: 3.12
Requires-Dist: numpy (>=1.14.0,<2.0.0)
Requires-Dist: scipy (>=1.6.0,<2.0.0)
Project-URL: Repository, https://github.com/getyourguide/basemath
